sharepoint_api/__init__.py
sharepoint_api/config.py
sharepoint_api/core/async_client.py
sharepoint_api/core/client.py
sharepoint_api/core/data_models.py
sharepoint_api/core/errors.py
sharepoint_api/logging.py
sharepoint_api_py-0.1.0.dist-info/LICENSE
sharepoint_api_py-0.1.0.dist-info/METADATA
sharepoint_api_py-0.1.0.dist-info/WHEEL
sharepoint_api_py-0.1.0.dist-info/RECORD
