Metadata-Version: 2.3
Name: sharepoint-api-py
Version: 0.1.0
Summary: Modern Python library for SharePoint API with httpx, async support, and automatic URL parsing
License: MIT
Keywords: sharepoint,microsoft,graph-api,httpx,async,office365
Author: Earl Dennison
Author-email: earl@example.com
Maintainer: Earl Dennison
Maintainer-email: earl@example.com
Requires-Python: >=3.10
Classifier: Development Status :: 4 - Beta
Classifier: Intended Audience :: Developers
Classifier: License :: OSI Approved :: MIT License
Classifier: Programming Language :: Python :: 3
Classifier: Programming Language :: Python :: 3.10
Classifier: Programming Language :: Python :: 3.11
Classifier: Programming Language :: Python :: 3.12
Classifier: Topic :: Office/Business
Classifier: Topic :: Software Development :: Libraries :: Python Modules
Provides-Extra: dev
Provides-Extra: http2
Requires-Dist: authlib (>=1.5.2)
Requires-Dist: black (>=24.0.0) ; extra == "dev"
Requires-Dist: coverage (>=7.4.0) ; extra == "dev"
Requires-Dist: h2 (>=4.1.0) ; extra == "http2"
Requires-Dist: httpx (>=0.28.1)
Requires-Dist: httpx-retries (>=0.3.2)
Requires-Dist: isort (>=5.13.0) ; extra == "dev"
Requires-Dist: mypy (>=1.8.0) ; extra == "dev"
Requires-Dist: pydantic (>=2.11.4)
Requires-Dist: pytest (>=8.3.5) ; extra == "dev"
Requires-Dist: pytest-asyncio (>=0.21.0) ; extra == "dev"
Requires-Dist: python-dotenv (>=1.1.0)
Requires-Dist: requests-mock (>=1.12.1) ; extra == "dev"
Project-URL: Bug Tracker, https://github.com/earldennison/sharepoint-api-py/issues
Project-URL: Changelog, https://github.com/earldennison/sharepoint-api-py/releases
Project-URL: Documentation, https://github.com/earldennison/sharepoint-api-py#readme
Project-URL: Homepage, https://github.com/earldennison/sharepoint-api-py
Project-URL: Repository, https://github.com/earldennison/sharepoint-api-py
